[{"Scientific Name":"Castilleja campestris var. succulenta","Common Name":"succulent owl's-clover","Groundwater Dependent":"Yes"},{"Scientific Name":"Orcuttia inaequalis","Common Name":"San Joaquin Valley Orcutt grass","Groundwater Dependent":"Yes"},{"Scientific Name":"Castilleja campestris var. succulenta","Common Name":"succulent owl's-clover","Groundwater Dependent":"Yes"},{"Scientific Name":"Pseudobahia bahiifolia","Common Name":"Hartweg's golden sunburst","Groundwater Dependent":"Yes"},{"Scientific Name":"Mylopharodon conocephalus","Common Name":"Hardhead","Groundwater Dependent":"Yes"},{"Scientific Name":"Desmocerus californicus dimorphus","Common Name":"valley elderberry longhorn beetle","Groundwater Dependent":"Yes"},{"Scientific Name":"Athene cunicularia","Common Name":"burrowing owl","Groundwater Dependent":"Yes"},{"Scientific Name":"Euderma maculatum","Common Name":"spotted bat","Groundwater Dependent":"Yes"},{"Scientific Name":"Spea hammondii","Common Name":"western spadefoot","Groundwater Dependent":"Yes"},{"Scientific Name":"Emys marmorata","Common Name":"western pond turtle","Groundwater Dependent":"Yes"},{"Scientific Name":"Buteo swainsoni","Common Name":"Swainson's hawk","Groundwater Dependent":"Nesting"},{"Scientific Name":"Sagittaria sanfordii","Common Name":"Sanford's arrowhead","Groundwater Dependent":"No"},{"Scientific Name":"Calycadenia hooveri","Common Name":"Hoover's calycadenia","Groundwater Dependent":"No"},{"Scientific Name":"Ambystoma californiense","Common Name":"California tiger salamander - central California DPS","Groundwater Dependent":"Partial"},{"Scientific Name":"Great Valley Mixed Riparian Forest","Common Name":"Great Valley Mixed Riparian Forest","Groundwater Dependent":"Mixed"},{"Scientific Name":"Sycamore Alluvial Woodland","Common Name":"Sycamore Alluvial Woodland","Groundwater Dependent":"Partial"},{"Scientific Name":"Northern Hardpan Vernal Pool","Common Name":"Northern Hardpan Vernal Pool","Groundwater Dependent":"Partial"},{"Scientific Name":"Linderiella occidentalis","Common Name":"California linderiella","Groundwater Dependent":"Partial"},{"Scientific Name":"Eryngium spinosepalum","Common Name":"spiny-sepaled button-celery","Groundwater Dependent":"Partial"},{"Scientific Name":"Downingia pusilla","Common Name":"dwarf downingia","Groundwater Dependent":"Partial"},{"Scientific Name":"Vulpes macrotis mutica","Common Name":"San Joaquin kit fox","Groundwater Dependent":"Associated"}]
